kst_instruct_following/__init__.py
kst_instruct_following/grpo_rewarder.py
kst_instruct_following/grpo_training.py
kst_instruct_following/merge_model.py
kst_instruct_following/processor.py
kst_instruct_following/reward_model_annoatation.py
kst_instruct_following/reward_model_training.py
kst_instruct_following/sft_training.py
kst_instruct_following/similarity_duplicator.py
kst_instruct_following/vllm_functions.py
kst_instruct_following/data_process/Config.py
kst_instruct_following/data_process/__init__.py
kst_instruct_following/data_process/first_turn_cleaner.py
kst_instruct_following/data_process/instruction_constructor.py
kst_instruct_following/data_process/instruction_follow_creator.py
kst_instruct_following/data_process/standard_datasets.py
kst_instruct_following/template/__init__.py
kst_instruct_following/template/first_turn_template.py
kst_instruct_following/template/reward_template.py
kst_instruct_following/template/system_template.py
kst_instruct_following-0.2.0.dist-info/METADATA
kst_instruct_following-0.2.0.dist-info/WHEEL
kst_instruct_following-0.2.0.dist-info/top_level.txt
kst_instruct_following-0.2.0.dist-info/RECORD
