Metadata-Version: 2.4
Name: kst_instruct_following
Version: 0.2.0
Summary: src for kst_instruct_following
Author: zhongp
Author-email: 1658763666@qq.com
Classifier: Programming Language :: Python :: 3
Classifier: License :: OSI Approved :: MIT License
Classifier: Operating System :: OS Independent
Requires-Python: >=3.6
Dynamic: author
Dynamic: author-email
Dynamic: classifier
Dynamic: description
Dynamic: description-content-type
Dynamic: requires-python
Dynamic: summary
